CausalDisco/__init__.py
CausalDisco/analytics.py
CausalDisco/baselines.py
CausalDisco/tests/__init__.py
CausalDisco/tests/tests.py
causaldisco-0.2.0.dist-info/WHEEL
causaldisco-0.2.0.dist-info/METADATA
causaldisco-0.2.0.dist-info/RECORD
