Metadata-Version: 2.1
Name: CausalDisco
Version: 0.2.0
Summary: Baseline algorithms and analytics tools for Causal Discovery.
Keywords: causality,causal discovery
Author: Alexander G. Reisach, Sebastian Weichwald
Classifier: Programming Language :: Python :: 3
Classifier: Topic :: Scientific/Engineering
Classifier: Topic :: Scientific/Engineering :: Mathematics
Classifier: Topic :: Scientific/Engineering :: Artificial Intelligence
Classifier: License :: OSI Approved :: BSD License
Classifier: Intended Audience :: Science/Research
Requires-Dist: numpy
Requires-Dist: scikit-learn
Requires-Dist: scipy
